geocode_mcp/server.py
geocode_mcp-0.2.0.dist-info/METADATA
geocode_mcp-0.2.0.dist-info/WHEEL
geocode_mcp-0.2.0.dist-info/entry_points.txt
geocode_mcp-0.2.0.dist-info/licenses/LICENSE
geocode_mcp-0.2.0.dist-info/RECORD
