Metadata-Version: 2.4
Name: geocode-mcp
Version: 0.2.0
Summary: MCP server for producing latitude/longitude coordinates for cities and areas using OpenStreetMap Nominatim API
Project-URL: Homepage, https://github.com/X-McKay/geocode-mcp
Project-URL: Repository, https://github.com/X-McKay/geocode-mcp
Project-URL: Issues, https://github.com/X-McKay/geocode-mcp/issues
Project-URL: Documentation, https://github.com/X-McKay/geocode-mcp#readme
Author-email: Al McKay <aldmckay@gmail.com>
License: MIT
License-File: LICENSE
Keywords: coordinates,latitude,longitude,mcp,openstreetmap
Requires-Python: >=3.12
Requires-Dist: aiohttp>=3.8.0
Requires-Dist: mcp>=1.0.0
Requires-Dist: ty>=0.0.1a12
Provides-Extra: dev
Requires-Dist: pre-commit>=3.0.0; extra == 'dev'
Requires-Dist: pytest-asyncio>=0.21.0; extra == 'dev'
Requires-Dist: pytest-cov>=4.0.0; extra == 'dev'
Requires-Dist: pytest>=7.0.0; extra == 'dev'
Requires-Dist: ruff>=0.1.0; extra == 'dev'
Requires-Dist: ty>=0.0.1a12; extra == 'dev'
